{"name":"building_point","type":"FeatureCollection"
,"crs":{"type":"name","properties":{"name":"EPSG:3857"}}
,"features":[
{"type":"Feature","geometry":{"type":"Point","coordinates":[-8237487.7,4966642.13]},"properties":{"osm_id":368043454,"building":"yes","building:levels":null,"height":null,"name":"Dudley Memorial","name:en":null,"craft":null,"office":null,"leisure":null,"shop":null,"addr:housenumber":null,"addr:housename":null,"addr:street":null,"addr:city":null,"addr:state":"NY","addr:postcode":null,"addr:place":null,"addr:country":null,"addr:hamlet":null,"addr:suburb":null,"addr:subdistrict":null,"addr:district":null,"addr:province":null,"addr:interpolation":null,"website":null,"contact:website":null,"phone":null,"contact:phone":null,"opening_hours":null,"brand":null,"construction":null,"tower:type":null,"disused":null,"z_order":null}}
,{"type":"Feature","geometry":{"type":"Point","coordinates":[-8236961.26,4967510.07]},"properties":{"osm_id":2322298894,"building":"residential","building:levels":null,"height":null,"name":null,"name:en":null,"craft":null,"office":null,"leisure":null,"shop":null,"addr:housenumber":"86","addr:housename":null,"addr:street":"Pierrepont Street","addr:city":"Brooklyn","addr:state":null,"addr:postcode":"11201","addr:place":null,"addr:country":null,"addr:hamlet":null,"addr:suburb":null,"addr:subdistrict":null,"addr:district":null,"addr:province":null,"addr:interpolation":null,"website":null,"contact:website":null,"phone":null,"contact:phone":null,"opening_hours":null,"brand":null,"construction":null,"tower:type":null,"disused":null,"z_order":null}}
,{"type":"Feature","geometry":{"type":"Point","coordinates":[-8236847.77,4967909.61]},"properties":{"osm_id":2329540407,"building":"office","building:levels":null,"height":null,"name":null,"name:en":null,"craft":null,"office":null,"leisure":null,"shop":null,"addr:housenumber":"80","addr:housename":null,"addr:street":"Pineapple Street","addr:city":null,"addr:state":null,"addr:postcode":"11201","addr:place":null,"addr:country":null,"addr:hamlet":null,"addr:suburb":null,"addr:subdistrict":null,"addr:district":null,"addr:province":null,"addr:interpolation":null,"website":null,"contact:website":null,"phone":null,"contact:phone":null,"opening_hours":null,"brand":null,"construction":null,"tower:type":null,"disused":null,"z_order":null}}
,{"type":"Feature","geometry":{"type":"Point","coordinates":[-8236776.49,4968232.71]},"properties":{"osm_id":368043432,"building":"yes","building:levels":null,"height":null,"name":"Henry Street Studios","name:en":null,"craft":null,"office":null,"leisure":null,"shop":null,"addr:housenumber":null,"addr:housename":null,"addr:street":null,"addr:city":null,"addr:state":"NY","addr:postcode":null,"addr:place":null,"addr:country":null,"addr:hamlet":null,"addr:suburb":null,"addr:subdistrict":null,"addr:district":null,"addr:province":null,"addr:interpolation":null,"website":null,"contact:website":null,"phone":null,"contact:phone":null,"opening_hours":null,"brand":null,"construction":null,"tower:type":null,"disused":null,"z_order":null}}
,{"type":"Feature","geometry":{"type":"Point","coordinates":[-8238119.04,4969071.91]},"properties":{"osm_id":368053948,"building":"yes","building:levels":null,"height":null,"name":"Hickson W Field Building","name:en":null,"craft":null,"office":null,"leisure":null,"shop":null,"addr:housenumber":"170, 176","addr:housename":null,"addr:street":"John Street","addr:city":"New York","addr:state":"NY","addr:postcode":null,"addr:place":"Manhattan Island","addr:country":"US","addr:hamlet":null,"addr:suburb":null,"addr:subdistrict":null,"addr:district":null,"addr:province":null,"addr:interpolation":null,"website":null,"contact:website":null,"phone":null,"contact:phone":null,"opening_hours":null,"brand":null,"construction":null,"tower:type":null,"disused":null,"z_order":null}}
,{"type":"Feature","geometry":{"type":"Point","coordinates":[-8238006.34,4969746.41]},"properties":{"osm_id":368053796,"building":"yes","building:levels":null,"height":null,"name":"Bache Plaza","name:en":null,"craft":null,"office":null,"leisure":null,"shop":null,"addr:housenumber":null,"addr:housename":null,"addr:street":null,"addr:city":null,"addr:state":"NY","addr:postcode":null,"addr:place":null,"addr:country":null,"addr:hamlet":null,"addr:suburb":null,"addr:subdistrict":null,"addr:district":null,"addr:province":null,"addr:interpolation":null,"website":null,"contact:website":null,"phone":null,"contact:phone":null,"opening_hours":null,"brand":null,"construction":null,"tower:type":null,"disused":null,"z_order":null}}
,{"type":"Feature","geometry":{"type":"Point","coordinates":[-8239667.83,4968818.82]},"properties":{"osm_id":368042725,"building":"yes","building:levels":null,"height":null,"name":"Liberty Gateway","name:en":null,"craft":null,"office":null,"leisure":null,"shop":null,"addr:housenumber":null,"addr:housename":null,"addr:street":null,"addr:city":null,"addr:state":"NY","addr:postcode":null,"addr:place":null,"addr:country":null,"addr:hamlet":null,"addr:suburb":null,"addr:subdistrict":null,"addr:district":null,"addr:province":null,"addr:interpolation":null,"website":null,"contact:website":null,"phone":null,"contact:phone":null,"opening_hours":null,"brand":null,"construction":null,"tower:type":null,"disused":null,"z_order":null}}
]}
